ibats_di_trader/__init__.py
ibats_di_trader/config.py
ibats_di_trader/agent/__init__.py
ibats_di_trader/agent/md_agent.py
ibats_di_trader/agent/td_agent.py
ibats_di_trader/backend/__init__.py
IBATS_DI_Trader-0.1.1.dist-info/LICENSE
IBATS_DI_Trader-0.1.1.dist-info/METADATA
IBATS_DI_Trader-0.1.1.dist-info/WHEEL
IBATS_DI_Trader-0.1.1.dist-info/top_level.txt
IBATS_DI_Trader-0.1.1.dist-info/RECORD
